firexbuilder/__init__.py
firexbuilder/_version.py
firexbuilder/build.py
firexbuilder-2.9.dist-info/LICENSE
firexbuilder-2.9.dist-info/METADATA
firexbuilder-2.9.dist-info/WHEEL
firexbuilder-2.9.dist-info/entry_points.txt
firexbuilder-2.9.dist-info/top_level.txt
firexbuilder-2.9.dist-info/zip-safe
firexbuilder-2.9.dist-info/RECORD
