Metadata-Version: 2.1
Name: firexbuilder
Version: 2.9
Summary: FireX builder
Home-page: https://github.com/FireXStuff/firexbuilder
Author: Core FireX Team
Author-email: firex-dev@gmail.com
License: BSD-3-Clause
Platform: UNKNOWN
Classifier: Programming Language :: Python :: 3
Classifier: Operating System :: OS Independent
Classifier: License :: OSI Approved :: BSD License
Requires-Dist: wheel
Requires-Dist: setuptools
Requires-Dist: twine
Requires-Dist: eventlet
Requires-Dist: coverage ==5.5
Requires-Dist: codecov
Requires-Dist: sphinx
Requires-Dist: sphinx-rtd-theme
Requires-Dist: sphinx-sitemap
